{"nodes": [{"id": "c_xampp_htdocs_lead_testsprite_tests_tmp_config_json", "label": "config.json", "file_type": "code", "source_file": "C:\\xampp\\htdocs\\lead\\testsprite_tests\\tmp\\config.json", "source_location": "L1"}, {"id": "tmp_config_status", "label": "status", "file_type": "code", "source_file": "C:\\xampp\\htdocs\\lead\\testsprite_tests\\tmp\\config.json", "source_location": "L2"}, {"id": "tmp_config_type", "label": "type", "file_type": "code", "source_file": "C:\\xampp\\htdocs\\lead\\testsprite_tests\\tmp\\config.json", "source_location": "L3"}, {"id": "tmp_config_scope", "label": "scope", "file_type": "code", "source_file": "C:\\xampp\\htdocs\\lead\\testsprite_tests\\tmp\\config.json", "source_location": "L4"}, {"id": "tmp_config_localendpoint", "label": "localEndpoint", "file_type": "code", "source_file": "C:\\xampp\\htdocs\\lead\\testsprite_tests\\tmp\\config.json", "source_location": "L5"}, {"id": "tmp_config_loginuser", "label": "loginUser", "file_type": "code", "source_file": "C:\\xampp\\htdocs\\lead\\testsprite_tests\\tmp\\config.json", "source_location": "L6"}, {"id": "tmp_config_loginpassword", "label": "loginPassword", "file_type": "code", "source_file": "C:\\xampp\\htdocs\\lead\\testsprite_tests\\tmp\\config.json", "source_location": "L7"}, {"id": "tmp_config_executionargs", "label": "executionArgs", "file_type": "code", "source_file": "C:\\xampp\\htdocs\\lead\\testsprite_tests\\tmp\\config.json", "source_location": "L8"}, {"id": "tmp_config_executionargs_projectname", "label": "projectName", "file_type": "code", "source_file": "C:\\xampp\\htdocs\\lead\\testsprite_tests\\tmp\\config.json", "source_location": "L9"}, {"id": "tmp_config_executionargs_projectpath", "label": "projectPath", "file_type": "code", "source_file": "C:\\xampp\\htdocs\\lead\\testsprite_tests\\tmp\\config.json", "source_location": "L10"}, {"id": "tmp_config_executionargs_testids", "label": "testIds", "file_type": "code", "source_file": "C:\\xampp\\htdocs\\lead\\testsprite_tests\\tmp\\config.json", "source_location": "L11"}, {"id": "tmp_config_executionargs_additionalinstruction", "label": "additionalInstruction", "file_type": "code", "source_file": "C:\\xampp\\htdocs\\lead\\testsprite_tests\\tmp\\config.json", "source_location": "L16"}, {"id": "tmp_config_executionargs_servermode", "label": "serverMode", "file_type": "code", "source_file": "C:\\xampp\\htdocs\\lead\\testsprite_tests\\tmp\\config.json", "source_location": "L17"}, {"id": "tmp_config_executionargs_envs", "label": "envs", "file_type": "code", "source_file": "C:\\xampp\\htdocs\\lead\\testsprite_tests\\tmp\\config.json", "source_location": "L18"}, {"id": "tmp_config_envs_api_key", "label": "API_KEY", "file_type": "code", "source_file": "C:\\xampp\\htdocs\\lead\\testsprite_tests\\tmp\\config.json", "source_location": "L19"}, {"id": "tmp_config_serverport", "label": "serverPort", "file_type": "code", "source_file": "C:\\xampp\\htdocs\\lead\\testsprite_tests\\tmp\\config.json", "source_location": "L22"}], "edges": [{"source": "c_xampp_htdocs_lead_testsprite_tests_tmp_config_json", "target": "tmp_config_status", "relation": "contains", "confidence": "EXTRACTED", "source_file": "C:\\xampp\\htdocs\\lead\\testsprite_tests\\tmp\\config.json", "source_location": "L2", "weight": 1.0}, {"source": "c_xampp_htdocs_lead_testsprite_tests_tmp_config_json", "target": "tmp_config_type", "relation": "contains", "confidence": "EXTRACTED", "source_file": "C:\\xampp\\htdocs\\lead\\testsprite_tests\\tmp\\config.json", "source_location": "L3", "weight": 1.0}, {"source": "c_xampp_htdocs_lead_testsprite_tests_tmp_config_json", "target": "tmp_config_scope", "relation": "contains", "confidence": "EXTRACTED", "source_file": "C:\\xampp\\htdocs\\lead\\testsprite_tests\\tmp\\config.json", "source_location": "L4", "weight": 1.0}, {"source": "c_xampp_htdocs_lead_testsprite_tests_tmp_config_json", "target": "tmp_config_localendpoint", "relation": "contains", "confidence": "EXTRACTED", "source_file": "C:\\xampp\\htdocs\\lead\\testsprite_tests\\tmp\\config.json", "source_location": "L5", "weight": 1.0}, {"source": "c_xampp_htdocs_lead_testsprite_tests_tmp_config_json", "target": "tmp_config_loginuser", "relation": "contains", "confidence": "EXTRACTED", "source_file": "C:\\xampp\\htdocs\\lead\\testsprite_tests\\tmp\\config.json", "source_location": "L6", "weight": 1.0}, {"source": "c_xampp_htdocs_lead_testsprite_tests_tmp_config_json", "target": "tmp_config_loginpassword", "relation": "contains", "confidence": "EXTRACTED", "source_file": "C:\\xampp\\htdocs\\lead\\testsprite_tests\\tmp\\config.json", "source_location": "L7", "weight": 1.0}, {"source": "c_xampp_htdocs_lead_testsprite_tests_tmp_config_json", "target": "tmp_config_executionargs", "relation": "contains", "confidence": "EXTRACTED", "source_file": "C:\\xampp\\htdocs\\lead\\testsprite_tests\\tmp\\config.json", "source_location": "L8", "weight": 1.0}, {"source": "tmp_config_executionargs", "target": "tmp_config_executionargs_projectname", "relation": "contains", "confidence": "EXTRACTED", "source_file": "C:\\xampp\\htdocs\\lead\\testsprite_tests\\tmp\\config.json", "source_location": "L9", "weight": 1.0}, {"source": "tmp_config_executionargs", "target": "tmp_config_executionargs_projectpath", "relation": "contains", "confidence": "EXTRACTED", "source_file": "C:\\xampp\\htdocs\\lead\\testsprite_tests\\tmp\\config.json", "source_location": "L10", "weight": 1.0}, {"source": "tmp_config_executionargs", "target": "tmp_config_executionargs_testids", "relation": "contains", "confidence": "EXTRACTED", "source_file": "C:\\xampp\\htdocs\\lead\\testsprite_tests\\tmp\\config.json", "source_location": "L11", "weight": 1.0}, {"source": "tmp_config_executionargs_testids", "target": "ref_tc006", "relation": "extends", "confidence": "EXTRACTED", "source_file": "C:\\xampp\\htdocs\\lead\\testsprite_tests\\tmp\\config.json", "source_location": "L11", "weight": 1.0, "context": "import"}, {"source": "tmp_config_executionargs_testids", "target": "ref_tc011", "relation": "extends", "confidence": "EXTRACTED", "source_file": "C:\\xampp\\htdocs\\lead\\testsprite_tests\\tmp\\config.json", "source_location": "L11", "weight": 1.0, "context": "import"}, {"source": "tmp_config_executionargs_testids", "target": "ref_tc022", "relation": "extends", "confidence": "EXTRACTED", "source_file": "C:\\xampp\\htdocs\\lead\\testsprite_tests\\tmp\\config.json", "source_location": "L11", "weight": 1.0, "context": "import"}, {"source": "tmp_config_executionargs", "target": "tmp_config_executionargs_additionalinstruction", "relation": "contains", "confidence": "EXTRACTED", "source_file": "C:\\xampp\\htdocs\\lead\\testsprite_tests\\tmp\\config.json", "source_location": "L16", "weight": 1.0}, {"source": "tmp_config_executionargs", "target": "tmp_config_executionargs_servermode", "relation": "contains", "confidence": "EXTRACTED", "source_file": "C:\\xampp\\htdocs\\lead\\testsprite_tests\\tmp\\config.json", "source_location": "L17", "weight": 1.0}, {"source": "tmp_config_executionargs", "target": "tmp_config_executionargs_envs", "relation": "contains", "confidence": "EXTRACTED", "source_file": "C:\\xampp\\htdocs\\lead\\testsprite_tests\\tmp\\config.json", "source_location": "L18", "weight": 1.0}, {"source": "tmp_config_executionargs_envs", "target": "tmp_config_envs_api_key", "relation": "contains", "confidence": "EXTRACTED", "source_file": "C:\\xampp\\htdocs\\lead\\testsprite_tests\\tmp\\config.json", "source_location": "L19", "weight": 1.0}, {"source": "c_xampp_htdocs_lead_testsprite_tests_tmp_config_json", "target": "tmp_config_serverport", "relation": "contains", "confidence": "EXTRACTED", "source_file": "C:\\xampp\\htdocs\\lead\\testsprite_tests\\tmp\\config.json", "source_location": "L22", "weight": 1.0}]}