{"nodes": [{"id": "c_xampp_htdocs_lead_api_core_jwt_php", "label": "jwt.php", "file_type": "code", "source_file": "C:\\xampp\\htdocs\\lead\\api\\core\\jwt.php", "source_location": "L1"}, {"id": "core_jwt_base64url_encode", "label": "base64url_encode()", "file_type": "code", "source_file": "C:\\xampp\\htdocs\\lead\\api\\core\\jwt.php", "source_location": "L8"}, {"id": "core_jwt_base64url_decode", "label": "base64url_decode()", "file_type": "code", "source_file": "C:\\xampp\\htdocs\\lead\\api\\core\\jwt.php", "source_location": "L12"}, {"id": "core_jwt_jwt_encode", "label": "jwt_encode()", "file_type": "code", "source_file": "C:\\xampp\\htdocs\\lead\\api\\core\\jwt.php", "source_location": "L16"}, {"id": "core_jwt_jwt_decode", "label": "jwt_decode()", "file_type": "code", "source_file": "C:\\xampp\\htdocs\\lead\\api\\core\\jwt.php", "source_location": "L32"}, {"id": "core_jwt_getbearertoken", "label": "getBearerToken()", "file_type": "code", "source_file": "C:\\xampp\\htdocs\\lead\\api\\core\\jwt.php", "source_location": "L57"}], "edges": [{"source": "c_xampp_htdocs_lead_api_core_jwt_php", "target": "core_jwt_base64url_encode", "relation": "contains", "confidence": "EXTRACTED", "source_file": "C:\\xampp\\htdocs\\lead\\api\\core\\jwt.php", "source_location": "L8", "weight": 1.0}, {"source": "c_xampp_htdocs_lead_api_core_jwt_php", "target": "core_jwt_base64url_decode", "relation": "contains", "confidence": "EXTRACTED", "source_file": "C:\\xampp\\htdocs\\lead\\api\\core\\jwt.php", "source_location": "L12", "weight": 1.0}, {"source": "c_xampp_htdocs_lead_api_core_jwt_php", "target": "core_jwt_jwt_encode", "relation": "contains", "confidence": "EXTRACTED", "source_file": "C:\\xampp\\htdocs\\lead\\api\\core\\jwt.php", "source_location": "L16", "weight": 1.0}, {"source": "c_xampp_htdocs_lead_api_core_jwt_php", "target": "core_jwt_jwt_decode", "relation": "contains", "confidence": "EXTRACTED", "source_file": "C:\\xampp\\htdocs\\lead\\api\\core\\jwt.php", "source_location": "L32", "weight": 1.0}, {"source": "c_xampp_htdocs_lead_api_core_jwt_php", "target": "core_jwt_getbearertoken", "relation": "contains", "confidence": "EXTRACTED", "source_file": "C:\\xampp\\htdocs\\lead\\api\\core\\jwt.php", "source_location": "L57", "weight": 1.0}, {"source": "core_jwt_jwt_encode", "target": "core_jwt_base64url_encode", "relation": "calls", "context": "call", "confidence": "EXTRACTED", "source_file": "C:\\xampp\\htdocs\\lead\\api\\core\\jwt.php", "source_location": "L23", "weight": 1.0}, {"source": "core_jwt_jwt_decode", "target": "core_jwt_base64url_encode", "relation": "calls", "context": "call", "confidence": "EXTRACTED", "source_file": "C:\\xampp\\htdocs\\lead\\api\\core\\jwt.php", "source_location": "L42", "weight": 1.0}, {"source": "core_jwt_jwt_decode", "target": "core_jwt_base64url_decode", "relation": "calls", "context": "call", "confidence": "EXTRACTED", "source_file": "C:\\xampp\\htdocs\\lead\\api\\core\\jwt.php", "source_location": "L48", "weight": 1.0}], "raw_calls": [{"caller_nid": "core_jwt_base64url_encode", "callee": "rtrim", "is_member_call": false, "source_file": "C:\\xampp\\htdocs\\lead\\api\\core\\jwt.php", "source_location": "L9"}, {"caller_nid": "core_jwt_base64url_encode", "callee": "strtr", "is_member_call": false, "source_file": "C:\\xampp\\htdocs\\lead\\api\\core\\jwt.php", "source_location": "L9"}, {"caller_nid": "core_jwt_base64url_encode", "callee": "base64_encode", "is_member_call": false, "source_file": "C:\\xampp\\htdocs\\lead\\api\\core\\jwt.php", "source_location": "L9"}, {"caller_nid": "core_jwt_base64url_decode", "callee": "base64_decode", "is_member_call": false, "source_file": "C:\\xampp\\htdocs\\lead\\api\\core\\jwt.php", "source_location": "L13"}, {"caller_nid": "core_jwt_base64url_decode", "callee": "str_pad", "is_member_call": false, "source_file": "C:\\xampp\\htdocs\\lead\\api\\core\\jwt.php", "source_location": "L13"}, {"caller_nid": "core_jwt_base64url_decode", "callee": "strtr", "is_member_call": false, "source_file": "C:\\xampp\\htdocs\\lead\\api\\core\\jwt.php", "source_location": "L13"}, {"caller_nid": "core_jwt_base64url_decode", "callee": "strlen", "is_member_call": false, "source_file": "C:\\xampp\\htdocs\\lead\\api\\core\\jwt.php", "source_location": "L13"}, {"caller_nid": "core_jwt_base64url_decode", "callee": "strlen", "is_member_call": false, "source_file": "C:\\xampp\\htdocs\\lead\\api\\core\\jwt.php", "source_location": "L13"}, {"caller_nid": "core_jwt_base64url_decode", "callee": "strlen", "is_member_call": false, "source_file": "C:\\xampp\\htdocs\\lead\\api\\core\\jwt.php", "source_location": "L13"}, {"caller_nid": "core_jwt_base64url_decode", "callee": "strlen", "is_member_call": false, "source_file": "C:\\xampp\\htdocs\\lead\\api\\core\\jwt.php", "source_location": "L13"}, {"caller_nid": "core_jwt_jwt_encode", "callee": "json_encode", "is_member_call": false, "source_file": "C:\\xampp\\htdocs\\lead\\api\\core\\jwt.php", "source_location": "L18"}, {"caller_nid": "core_jwt_jwt_encode", "callee": "time", "is_member_call": false, "source_file": "C:\\xampp\\htdocs\\lead\\api\\core\\jwt.php", "source_location": "L19"}, {"caller_nid": "core_jwt_jwt_encode", "callee": "time", "is_member_call": false, "source_file": "C:\\xampp\\htdocs\\lead\\api\\core\\jwt.php", "source_location": "L20"}, {"caller_nid": "core_jwt_jwt_encode", "callee": "json_encode", "is_member_call": false, "source_file": "C:\\xampp\\htdocs\\lead\\api\\core\\jwt.php", "source_location": "L21"}, {"caller_nid": "core_jwt_jwt_encode", "callee": "hash_hmac", "is_member_call": false, "source_file": "C:\\xampp\\htdocs\\lead\\api\\core\\jwt.php", "source_location": "L26"}, {"caller_nid": "core_jwt_jwt_decode", "callee": "explode", "is_member_call": false, "source_file": "C:\\xampp\\htdocs\\lead\\api\\core\\jwt.php", "source_location": "L33"}, {"caller_nid": "core_jwt_jwt_decode", "callee": "count", "is_member_call": false, "source_file": "C:\\xampp\\htdocs\\lead\\api\\core\\jwt.php", "source_location": "L34"}, {"caller_nid": "core_jwt_jwt_decode", "callee": "hash_hmac", "is_member_call": false, "source_file": "C:\\xampp\\htdocs\\lead\\api\\core\\jwt.php", "source_location": "L42"}, {"caller_nid": "core_jwt_jwt_decode", "callee": "hash_equals", "is_member_call": false, "source_file": "C:\\xampp\\htdocs\\lead\\api\\core\\jwt.php", "source_location": "L44"}, {"caller_nid": "core_jwt_jwt_decode", "callee": "json_decode", "is_member_call": false, "source_file": "C:\\xampp\\htdocs\\lead\\api\\core\\jwt.php", "source_location": "L48"}, {"caller_nid": "core_jwt_jwt_decode", "callee": "isset", "is_member_call": false, "source_file": "C:\\xampp\\htdocs\\lead\\api\\core\\jwt.php", "source_location": "L49"}, {"caller_nid": "core_jwt_jwt_decode", "callee": "time", "is_member_call": false, "source_file": "C:\\xampp\\htdocs\\lead\\api\\core\\jwt.php", "source_location": "L49"}, {"caller_nid": "core_jwt_getbearertoken", "callee": "isset", "is_member_call": false, "source_file": "C:\\xampp\\htdocs\\lead\\api\\core\\jwt.php", "source_location": "L59"}, {"caller_nid": "core_jwt_getbearertoken", "callee": "trim", "is_member_call": false, "source_file": "C:\\xampp\\htdocs\\lead\\api\\core\\jwt.php", "source_location": "L60"}, {"caller_nid": "core_jwt_getbearertoken", "callee": "isset", "is_member_call": false, "source_file": "C:\\xampp\\htdocs\\lead\\api\\core\\jwt.php", "source_location": "L61"}, {"caller_nid": "core_jwt_getbearertoken", "callee": "trim", "is_member_call": false, "source_file": "C:\\xampp\\htdocs\\lead\\api\\core\\jwt.php", "source_location": "L62"}, {"caller_nid": "core_jwt_getbearertoken", "callee": "function_exists", "is_member_call": false, "source_file": "C:\\xampp\\htdocs\\lead\\api\\core\\jwt.php", "source_location": "L63"}, {"caller_nid": "core_jwt_getbearertoken", "callee": "apache_request_headers", "is_member_call": false, "source_file": "C:\\xampp\\htdocs\\lead\\api\\core\\jwt.php", "source_location": "L64"}, {"caller_nid": "core_jwt_getbearertoken", "callee": "array_combine", "is_member_call": false, "source_file": "C:\\xampp\\htdocs\\lead\\api\\core\\jwt.php", "source_location": "L65"}, {"caller_nid": "core_jwt_getbearertoken", "callee": "array_map", "is_member_call": false, "source_file": "C:\\xampp\\htdocs\\lead\\api\\core\\jwt.php", "source_location": "L65"}, {"caller_nid": "core_jwt_getbearertoken", "callee": "array_keys", "is_member_call": false, "source_file": "C:\\xampp\\htdocs\\lead\\api\\core\\jwt.php", "source_location": "L65"}, {"caller_nid": "core_jwt_getbearertoken", "callee": "array_values", "is_member_call": false, "source_file": "C:\\xampp\\htdocs\\lead\\api\\core\\jwt.php", "source_location": "L65"}, {"caller_nid": "core_jwt_getbearertoken", "callee": "isset", "is_member_call": false, "source_file": "C:\\xampp\\htdocs\\lead\\api\\core\\jwt.php", "source_location": "L66"}, {"caller_nid": "core_jwt_getbearertoken", "callee": "trim", "is_member_call": false, "source_file": "C:\\xampp\\htdocs\\lead\\api\\core\\jwt.php", "source_location": "L67"}, {"caller_nid": "core_jwt_getbearertoken", "callee": "empty", "is_member_call": false, "source_file": "C:\\xampp\\htdocs\\lead\\api\\core\\jwt.php", "source_location": "L71"}, {"caller_nid": "core_jwt_getbearertoken", "callee": "preg_match", "is_member_call": false, "source_file": "C:\\xampp\\htdocs\\lead\\api\\core\\jwt.php", "source_location": "L72"}]}